odoo/addons/sale_order_metadata/__init__.py
odoo/addons/sale_order_metadata/__manifest__.py
odoo/addons/sale_order_metadata/models/__init__.py
odoo/addons/sale_order_metadata/models/sale_order.py
odoo/addons/sale_order_metadata/models/sale_order_metadata_line.py
odoo/addons/sale_order_metadata/security/ir.model.access.csv
odoo/addons/sale_order_metadata/views/sale_order.xml
odoo_addon_sale_order_metadata-16.0.0.1.0.dist-info/METADATA
odoo_addon_sale_order_metadata-16.0.0.1.0.dist-info/WHEEL
odoo_addon_sale_order_metadata-16.0.0.1.0.dist-info/top_level.txt
odoo_addon_sale_order_metadata-16.0.0.1.0.dist-info/RECORD
