Metadata-Version: 2.1
Name: odoo-addon-sale-order-metadata
Version: 16.0.0.1.0
Summary: Add metadata to sale order
Home-page: 
Author: Coopdevs Treball SCCL
Classifier: Programming Language :: Python
Classifier: Framework :: Odoo
Classifier: Framework :: Odoo :: 16.0
Requires-Python: >=3.10
Requires-Dist: odoo-addon-metadata <16.1dev,>=16.0dev
Requires-Dist: odoo <16.1dev,>=16.0a
